{"aggregate_scope":{"aggregate_label":"grid_frequency","blocked_cells_in_denominator":true,"denominator_basis":"all_raw_cells","denominator_policy":"all_enumerated_cells","full_grid_run":false,"raw_cell_artifact_kind":"fbt_atlas_v1_raw_cell_table","reads_config":false,"recomputes_cells":false,"source":"raw_cell_artifact_only","source_theorem_result_claim":false,"tie_sensitive_cells_in_denominator":true},"artifact_kind":"fbt_atlas_v1_aggregate_report","assumption_ids":["ASM-FBT-0001","ASM-FBT-0002","ASM-FBT-0003","ASM-FBT-0004"],"claim_boundary":{"allowed":["This artifact aggregates status counts from one atlas v1 raw-cell artifact.","The reported values are grid_frequency summaries over the input raw cells only."],"forbidden":["The full finite atlas has been run.","Theorem 4 has been implemented, proved, reproduced, or reviewed.","A project grid_frequency is a source theorem result.","The result says anything about real perception, consciousness, spacetime, ontology, biology, ML/RL, figures, UI, or evolutionary dynamics."]},"claim_ids":["CLM-FBT-ATLAS-001"],"epistemic_status":"E","grid_version":"fbt_atlas_v1_draft","input_artifact":{"artifact_kind":"fbt_atlas_v1_raw_cell_table","path":"C:\\Users\\user\\Fitness, Truth & Structure Lab\\results\\raw\\EXP-TASK-004-FBT-ATLAS-V1-RAW-CELLS-20260702T080919Z-0AE3BB9C\\fbt_atlas_v1_raw_cells.json","raw_cell_count":144,"sha256":"582e7e50fd8b1bfab149feab6e00d80cd95bda29268ff6fec99e0a5ed4748613"},"limitations":["The aggregate is derived only from the provided raw-cell JSON artifact.","The command does not read the v1 config and does not regenerate cells.","The output remains pending independent review as part of the atlas v1 bundle."],"schema_version":"1.0","source_ids":["SRC-FBT-2021"],"summary":{"grid_frequencies_by_status":{"blocked_zero_marginal":{"denominator":16,"label":"5/16","numerator":5},"map_tie_policy_sensitive":{"denominator":144,"label":"11/144","numerator":11},"same_best_observation":{"denominator":144,"label":"17/144","numerator":17},"truth_decision_tie":{"denominator":144,"label":"71/144","numerator":71}},"status_counts":{"blocked_zero_marginal":45,"map_tie_policy_sensitive":11,"same_best_observation":17,"truth_decision_tie":71},"status_rows":[{"count":45,"grid_frequency":{"denominator":16,"label":"5/16","numerator":5},"status":"blocked_zero_marginal"},{"count":11,"grid_frequency":{"denominator":144,"label":"11/144","numerator":11},"status":"map_tie_policy_sensitive"},{"count":17,"grid_frequency":{"denominator":144,"label":"17/144","numerator":17},"status":"same_best_observation"},{"count":71,"grid_frequency":{"denominator":144,"label":"71/144","numerator":71},"status":"truth_decision_tie"}],"total_raw_cells":144},"task_ids":["TASK-004-FBT-ATLAS-V1-SPEC","TASK-004-FBT-ATLAS-V1-ENGINE","TASK-004-FBT-ATLAS-V1-AGGREGATE"]}